flowdump/__init__.py
flowdump/core.py
flowdump/nipype_report_parser.py
flowdump/utils.py
flowdump/workflow_json.py
flowdump-0.1.2.dist-info/LICENSE
flowdump-0.1.2.dist-info/METADATA
flowdump-0.1.2.dist-info/WHEEL
flowdump-0.1.2.dist-info/RECORD
