Metadata-Version: 2.1
Name: flowdump
Version: 0.1.2
Summary: NiPype-1 workflow serializer.
License: LGPL-2.1
Author: Florian Rupprecht
Author-email: floruppr@gmail.com
Requires-Python: >=3.7
Classifier: License :: OSI Approved
Classifier: Programming Language :: Python :: 3
Classifier: Programming Language :: Python :: 3.7
Classifier: Programming Language :: Python :: 3.8
Classifier: Programming Language :: Python :: 3.9
Classifier: Programming Language :: Python :: 3.10
Classifier: Programming Language :: Python :: 3.11
Requires-Dist: nipype (>=1.0.0,<2.0.0)
